bodywork_pipeline_utils/__init__.py
bodywork_pipeline_utils/logging.py
bodywork_pipeline_utils/py.typed
bodywork_pipeline_utils/aws/__init__.py
bodywork_pipeline_utils/aws/artefacts.py
bodywork_pipeline_utils/aws/datasets.py
bodywork_pipeline_utils/aws/models.py
bodywork_pipeline_utils-0.1.5.dist-info/LICENSE
bodywork_pipeline_utils-0.1.5.dist-info/METADATA
bodywork_pipeline_utils-0.1.5.dist-info/WHEEL
bodywork_pipeline_utils-0.1.5.dist-info/top_level.txt
bodywork_pipeline_utils-0.1.5.dist-info/zip-safe
bodywork_pipeline_utils-0.1.5.dist-info/RECORD
